{"id":"","source":"O!Business_ИП жана юридикалык жактарга кызмат көрсөтүү боюнча коомдук сунуш 25.12.2025.pdf","category":"","subcategory":"","section":"Кошумча 4","title":"","content":"Кошумча 4 Долбоордун комплексдүү банктын кызмат көрсөтүүсү боюнча жеке предприниматель юридикалык жакты «O!Business» БАНК СЧЕТИН АЧУУ ЖАНА ЖҮРГҮЗҮҮНҮН ШАРТТАРЫ 1. Бул Банктын эсептерин ачуу жана жүргүзүү боюнча шарттар (арызда – Шарттар) Клиенттин банктын эсептерин ачуу, жүргүзүү жана жабуу тартибин аныктайт жана «O!Business» (арызда – Договор) боюнча комплексдүү банктын кызмат көрсөтүүсүнүн Договорунун ажырагыс бөлүгү болуп саналат. 2. Договордун жана Шарттардын алкагында, Банк Клиенттин арызы боюнча төмөнкү түрдөгү банктын эсептерин ачат: эсептик эсеп; мөөнөттүү банктын депозиттик эсеби; атайын эсеп. 3. Клиент-жеке предприниматель үчүн банктын эсебин ачуу биринчи жолу кайрылганда, Клиент-жеке предпринимательдин же анын ыйгарым укуктуу өкүлүнүн катышуусунда жүргүзүлөт, тиешелүү ыйгарым укуктарды тастыктаган документтердин туура түрдө толтурулгандыгы менен. 4. Клиент-юридикалык жак үчүн банктын эсебин ачуу, ыйгарым укуктуу өкүлдүн катышуусунда жүргүзүлөт, анын эсепти ачуу ыйгарым укуктарын тастыктаган документтери болушу керек. 5. Банк Клиенттин арызына ылайык, төмөнкү шарттарда банктын эсебин ачат: Кыргыз Республикасынын мыйзамдарына жана Кыргыз Республикасынын Улуттук банкынын нормативдик укуктук актыларына ылайык, эсепти ачуу үчүн зарыл болгон документтердин толук пакетин берүү; белгиленген тартипте идентификациядан жана верификациядан өтүү. 6. Банктын эсебин ачуу үчүн, Клиент-жеке предприниматель Банкка төмөнкү документтерди сунушташы керек: 6.1. Клиент-жеке предприниматель тарабынан кагаз түрүндө же электрондук документ түрүндө, электрондук кол тамга менен кол коюлган, белгиленген формадагы толтурулган арыз; 6.2. Клиент-жеке предпринимательдин жеке башын тастыктаган документ; 6.3. ыйгарым укуктуу орган тарабынан берилген, жеке предприниматель катары мамлекеттик каттоодон (кайра каттоодон) өткөндүгүн тастыктаган документтин көчүрмөсү же мамлекеттик каттоодон (патент же салык кызматынын органынан соода зонасында салык төлөө боюнча чечим) өткөндүгүн тастыктаган документтин көчүрмөсү; 6.4. Клиент-жеке предпринимательдин Эркин экономикалык зонада субъект катары каттоодон өткөндүгүн тастыктаган күбөлүк (экономикалык ишмердүүлүктүн атайын режиминде катталган Клиент-жеке предпринимательлер үчүн) же Кыргыз Республикасынын Жогорку технологиялар паркынын резиденти катары каттоодон өткөндүгүн тастыктаган күбөлүк (атайын укуктук, салык режиминде катталган Клиент-жеке предпринимательлер үчүн). 7. Банктын эсебин ачуу үчүн, Клиент-юридикалык жак Банкка төмөнкү документтерди сунушташы керек: 7.1. карточкадагы кол тамгалардын үлгүсүндө көрсөтүлгөн, келишимдерди жана финансылык документтерди кол коюу ыйгарым укуктарына ээ болгон адамдар тарабынан кол коюлган, белгиленген формадагы толтурулган арыз, юридикалык жактын мөөрү менен бекитилген; 7.2. юридикалык жактын мамлекеттик каттоодон (кайра каттоодон) өткөндүгү тууралуу маалымкат (күбөлүк); 7.3. юридикалык жактын Эркин экономикалык зонада субъект катары каттоодон өткөндүгүн тастыктаган күбөлүк (экономикалык ишмердүүлүктүн атайын режиминде катталган юридикалык жактар үчүн); 7.4. Кыргыз Республикасынын Жогорку технологиялар паркынын резиденти катары каттоодон өткөндүгүн тастыктаган күбөлүк (атайын укуктук, салык режиминде катталган юридикалык жактар үчүн); 7.5. юридикалык жактын уюштуруу документтери, уюштуруу-укуктук формасына жараша, өзгөртүүлөр жана толуктоолор менен; 7.6. Кыргыз Республикасынын мыйзамдарына жана (же) келип чыккан өлкөгө ылайык, милдеттүү лицензиялоого тийиш болгон ишмердүүлүктү жүргүзгөн учурда юридикалык жактын лицензиясы; 7.7. нотариалдык түрдө бекитилген кол тамгалардын үлгүсү жана мөөрдүн оттиски менен карточка; 7.8. юридикалык жактын акча каражаттарын (банктын эсептерин) башкарууга ыйгарым укуктуу адамдын жеке башын тастыктаган документ. 8. Клиенттин же үчүнчү жактын акча каражаттарын, Клиенттин банктын эсебинде турган акча каражаттарын башкарууга ыйгарым укуктарын тастыктаган негизги документ, ошондой эле кол тамгасынын чыныгы экендигин тастыктаган документ - кол тамгалардын үлгүсү жана мөөрдүн оттиски менен карточка. 9. Эгерде Банктын атынан үчүнчү жак чыгып жатса, Банкка анын жеке башын тастыктаган документ - кагаз түрүндө же мамлекеттик маалымат системаларынан алынган санариптик форматта, ошондой эле эсепти ачуу үчүн тиешелүү ыйгарым укуктарын тастыктаган документтерди сунуштоо керек. 10. Эгерде банктын эсебин ачуу үчүн сунушталуучу документтин оригиналы чет тилде болсо, Клиент Банкка мамлекеттик тилге жана зарыл болсо расмий тилге которулган документтерди, котормо мекемеси тарабынан бекитилген. 11. Эгерде Клиенттин Банкка сунуштаган документтери Гаага конвенциясына катышпаган өлкөдө берилсе, алар Кыргыз Республикасынын ыйгарым укуктуу органынын Консулдук кызматына легализацияланууга тийиш. Эгерде Банкка сунушталган документтер Гаага конвенциясына катышкан өлкөдө берилсе, алардын чыныгы экендиги апостил менен тастыкталат. 12. Клиенттин жана (же) анын өкүлүнүн кошулуу арызын кол коюу, төмөнкүлөрдү тастыктагандыгын билдирет: Клиент «O!Business» боюнча жеке предприниматель юридикалык жак үчүн комплексдүү банктын кызмат көрсөтүүсү боюнча Договордун мазмуну менен тааныш; Клиент Договор жана Шарттарда белгиленген банктын эсебин ачуу, жүргүзүү жана жабуу боюнча бардык шарттарды кабыл алат; Договор жана ушул Шарттар Клиент үчүн жүк салуучу же анын акылга сыярлык кызыкчылыктарына каршы келген жоболорду камтыбайт; Договордун бардык жоболору жана Шарттар толугу менен Клиенттин кызыкчылыктарын жана эркиндигин чагылдырат; Договорду түзүү, ушул Шарттарды кабыл алуу жана алардын жоболорун, анын ичинде банктын эсебин ачуу, Клиенттин уюштуруу жана башка ички документтерине каршы келбейт; Клиент Договорду түзүү, Шарттарды кабыл алуу жана банктын эсебин ачуу үчүн бардык зарыл процедураларды аткарган. 13. Банк Клиентке эсепти ачууга же эсеп боюнча операцияларды жүргүзүүгө баш тартууга укуктуу, эгерде: эсепти ачуу жана (же) операцияларды жүргүзүү үчүн талап кылынган тиешелүү документтер берилбесе, Клиентти жана (же) анын бенефициардык ээси идентификациялоо жана верификациялоо, ошондой эле башка тиешелүү текшерүү чараларын жүргүзүү; жалган документтер берилсе. 14. Клиенттин эсебин ачуу жана жүргүзүү, ошондой эле Клиенттин эсеби боюнча операцияларды жүргүзүү, Банк тарабынан белгиленген тарифтерге ылайык, акча төлөө негизинде жүргүзүлөт. Банк тарабынан актуалдуу тарифтер жөнүндө маалымат Банктың расмий сайтындагы «Тарифтер» бөлүмүндө жайгаштырылган, ошондой эле Клиентке Банктың бөлүмдөрүндө таанышуу үчүн жеткиликтүү. 15. Эгерде Договордо жана ушул Шарттарда башкача каралбаса, Клиент арыз (арыздар) негизинде бир же бир нече эсептерди ачууга укуктуу. Ошол эле учурда, ушул Шарттар Клиент тарабынан ачылган ар бир эсепке таралат. 16. Клиенттин эсеби улуттук жана чет элдик валюталарда ачылып жана жүргүзүлүшү мүмкүн, эгерде Кыргыз Республикасынын мыйзамдарында башкача каралбаса. 17. Негизги банктык эсепти улуттук валютада ачкандан кийин, чет элдик валютадагы кийинки эсептерди Клиент O!Business мобилдик банкинг системасында онлайн режиминде арыздарды түзүү аркылуу ача алат. 18. Клиент чет элдик валютада банктык эсеп ачуу жана жүргүзүү менен байланышкан тобокелдиктерди өзүнө алат, бул Кыргыз Республикасынын мыйзамдары жана (же) чет элдик мыйзамдар тарабынан белгиленген чектөөлөр менен байланыштуу болушу мүмкүн, чет элдик валютага, анын ичинде, бирок, чектелбестен, валюталык контролду же валюталык чектөөлөрдү киргизүү, ошондой эле салык же башка милдеттүү төлөмдөр, алар банктык эсепте турган акча каражаттарына же алардын колдонулушуна таралышы мүмкүн. 19. Банктык эсепти тейлөө жана банктык эсеп боюнча операцияларды аткаруу Банктын операциялык күнү ичинде жүргүзүлөт, анын узактыгы ар кандай бөлүмдөрдө (филиалдар, сактык кассалары, чыгуу кассалары) ар башка болушу мүмкүн. Операциялык күн валюталардын түрлөрү жана Банктын көрсөтүп жаткан кызматтары боюнча, ошондой эле Банктын Клиент менен банктык эсепти жүргүзүүдө өз ара аракеттенүү каналдары боюнча белгилениши мүмкүн. Операциялык күндүн узактыгы белгиленет жана Клиентке Банктын бөлүмдөрүндө Клиенттин карап чыгышы үчүн жеткиликтүү жерде мындай маалыматты жайгаштыруу аркылуу маалымдалат, ошондой эле Банктын тандоосу боюнча башка жолдор менен. 20. Банк Клиенттин банктык эсебине келип түшкөн акча каражаттарын тиешелүү валютада, Банктын тиешелүү төлөм буйругун алган күндөн кийинки күнү кечиктирбестен эсептейт. 21. Башка банктардан жана кандайдыр бир үчүнчү жактардан, анын ичинде QR-кодду колдонуу менен келген төлөмдөр жана (же) акча которуулар, Банктын Клиенттин банктык эсебине, мындай төлөмдөр же акча которууларды алуу менен байланышкан комиссиялар жана чыгымдарды (эгер алар Банктын күчүндө болгон тарифтерге ылайык алынуусу керек болсо) алып салгандан кийин, Кыргыз Республикасынын мыйзамдары тарабынан белгиленген мөөнөттө эсептелет. 22. Клиент тарабынан Банкка операциялык күндүн аяктагандан кийин жөнөтүлгөн төлөм буйруктары, кийинки операциялык күндүн башында Банктын алган деп эсептелет. 23. Клиенттин төлөм буйруктары, анын ичинде салык жана бюджетке башка милдеттүү төлөмдөрдү төлөө боюнча, тек гана операциялык күндүн ичинде кабыл алынат. 24. Клиент Банктан акча каражаттарын өзүнүн банктык эсептеринен мезгил-мезгили менен которуу боюнча буйрук берүүгө укуктуу. Банк Клиенттин буйруктарын, буйрукка ылайык банктык эсепте жетиштүү акча каражаттары болгондо, буйруктун күчүндө болгон мөөнөттө аткарат. 25. Клиенттин чет элдик валютадагы банктык эсеп боюнча операциялары, операциялар жүргүзүлгөн учурда Банктын белгилеген алмашуу курсу боюнча жүргүзүлөт. 26. Клиент банктык эсептин валютасында сумма эсепке алынуусуна макулдугун берет, бул алмашуу курсу боюнча Банктын белгилеген алмашуу курсу менен конвертациялоо аркылуу, акча которуу (же) төлөм келген учурда, төлөм валютасы банктык эсептин валютасына туура келбеген учурда, Банктын конвертациялоо үчүн комиссиялык акысы кармалып. 27. Чет элдик валютадагы бардык операциялар, анын ичинде банктык эсеп боюнча төлөмдөр жана (же) акча которуулар, чет элдик валюта боюнча банктык эсепте конвертациялоо, ошондой эле валюталык операцияларга тиешелүү башка операциялар Кыргыз Республикасынын мыйзамдарынын талаптарын, Банктын ички талаптарын жана ушул Шарттарды эске алуу менен жүргүзүлөт. 28. Клиент тарабынан башталган төлөм документи, эгер Банк тарабынан төлөм документин аткарбоо жөнүндө билдирүү алынбаса, Клиенттин төлөм буйругун алган күндөн кийинки бир операциялык күндүн ичинде аткарылган деп эсептелет. 29. Банк операцияны жүргүзүүдөн же банктык эсеп боюнча маалымат берүүдөн баш тартууга укуктуу, эгер Клиент Договордо жана ушул Шарттарда белгиленген тартипте идентификацияланбаган жана верификацияланбаган болсо, ошондой эле төлөм же акча которуу жүргүзүлгөн күнү банктык эсепте акча каражаттарынын жоктугу же жетишсиздиги болсо. 30. Банк мүмкүн болгон кечиктирүүлөр, жоготуулар жана (же) башка кесепеттер үчүн жоопкерчилик тартпайт, эгер алар кабыл алуучунун реквизиттерин туура эмес көрсөтүү, анын ичинде кабыл алуучу банктын реквизиттери, жөнөтүүчү банк же корреспондент банк тарабынан кеткен каталар жана башка себептер менен байланыштуу болсо, же операция жана (же) операциянын катышуучулары чет өлкөлөрдүн эл аралык чектөө чаралары (экономикалык санкциялар) киргизилген адамдар менен байланыштуу болсо. 31. Договорго ылайык, Клиент Банкка Клиенттин Банкта ачылган банктык эсептеринен акча алуу боюнча алдын ала макулдугун берет, Банк тарабынан коюлган талаптардын негизинде (банктык эсепти түздөн-түз дебеттөө). 32. Клиент менен келишим түзүлгөн адамдын талабына ылайык, Клиенттин банктык эсебинен акча алуу, Клиенттин макулдугу жок, Банк тарабынан түздөн-түз дебеттөө жолу менен жүргүзүлөт, бул үчүн Клиенттин макулдугу көрсөтүлгөн арыздын негизинде, ошондой эле төмөнкү документтердин негизинде: Келишимдин жана ага кошумча келишимдердин көчүрмөсү (эгер бар болсо);  Кыргыз Республикасынын мыйзамдарына ылайык берилген төлөм документтери. 33. Клиент Кыргыз Республикасынын мыйзамдары тарабынан белгиленген учурларда, Банк Клиенттин төлөм буйруктары жана буйруктары жок, Клиенттин эсептеринен акча каражаттарын алуу боюнча милдеттүү экенин кабыл алат. 34. Банк Клиенттин тейлөө мезгилинде Клиенттен кошумча маалымат жана документтерди талап кылууга укуктуу, булар пайда алуучуларды, акча каражаттарынын келип чыгуу булагын, операциялардын мыйзамдуулугун Кыргыз Республикасынын нормативдик укуктук актыларына ылайык аныктоого мүмкүндүк берет. 35. Банк Клиент тарабынан төлөм реквизиттерин көрсөтүүдө кеткен каталарды, Банктын операцияларды жүргүзүү үчүн талап кылган документтерди бербөө же толук эмес (так эмес) документтерди берүү учурларын аныктагандан кийин Клиенттин буйруктарын жана буйруктарын аткаруудан баш тартууга укуктуу, ошондой эле операция Кыргыз Республикасынын мыйзамдарына, Банктын ички талаптарына жана Договордун шарттарына каршы келген учурда. 36. Клиенттин маалыматтарында, анын ичинде жеке маалыматтарда, юридикалык даректе, негиздөөчү документтерде ж.б. өзгөртүүлөр болгон учурда, Банк үчүн маанилүү болушу мүмкүн, Клиент мындай өзгөртүүлөрдөн кийин 5 (беш) жумушчу күндүн ичинде Банкка жазуу жүзүндө билдирүүгө милдеттүү, бул үчүн документтердин оригиналдарын же күбөлөндүрүлгөн көчүрмөлөрүн берүү менен. Ар кандай өзгөртүүлөр Банк үчүн, Клиенттен билдирүү жана тиешелүү документтерди кабыл алгандан кийин гана күчүнө кирет. 37. Эсепти жабуу Кыргыз Республикасынын мыйзамдары жана Договор боюнча белгиленген негиздер жана тартип боюнча жүргүзүлөт.","page_numbers":[17,18,19,20,21]}
