{
  "model_name": "bge-m3",
  "language": "en",
  "collection_name": "ru_common_bge_m3_chunk1000_overlap150",
  "total_questions": 127,
  "evaluated_questions": 127,
  "failed_questions": 0,
  "recall@1": 0.5984251968503937,
  "recall@3": 0.7086614173228346,
  "recall@5": 0.7559055118110236,
  "mrr": 0.6632170978627672,
  "ndcg": 0.8097599996203367,
  "avg_latency_ms": 171.80002046616997,
  "median_latency_ms": 167.5994999241084,
  "run_id": "ru_common_bge-m3_en_russian_part_3.12.filtered.fixed_questions_en.repaired.jsonl",
  "question_file": "russian_part_3.12.filtered.fixed_questions_en.repaired.jsonl",
  "question_file_path": "C:\\Users\\1000001392\\.vscode\\ru_common\\ru_ru_metadata\\russian\\russian_3\\russian_part_3.12.filtered.fixed_questions_en.repaired.jsonl",
  "frozen": {
    "preprocessing": {
      "lowercase": false,
      "remove_special_chars": false,
      "strip_whitespace": true,
      "normalize_unicode": true
    },
    "chunking": {
      "strategy": "fixed",
      "chunk_size": 1000,
      "overlap": 150
    },
    "embedding": {
      "batch_size": 64
    },
    "retrieval": {
      "top_k": 10
    }
  },
  "machine": "UCA-NR-NBK-HL9"
}