{
  "model_name": "bge-m3",
  "language": "ru",
  "collection_name": "ru_common_bge_m3_chunk200_overlap100",
  "total_questions": 87,
  "evaluated_questions": 87,
  "failed_questions": 0,
  "recall@1": 0.5287356321839081,
  "recall@3": 0.7126436781609196,
  "recall@5": 0.8275862068965517,
  "mrr": 0.6433223864258347,
  "ndcg": 1.041680231273858,
  "avg_latency_ms": 141.56020344838825,
  "median_latency_ms": 141.36030000372557,
  "run_id": "ru_common_bge-m3_ru_opio_all_questions_ru.repaired.jsonl",
  "question_file": "opio_all_questions_ru.repaired.jsonl",
  "question_file_path": "C:\\Users\\1000001392\\.vscode\\ru_common\\ru_ru_metadata\\opio\\opio_all_questions_ru.repaired.jsonl",
  "frozen": {
    "preprocessing": {
      "lowercase": false,
      "remove_special_chars": false,
      "strip_whitespace": true,
      "normalize_unicode": true
    },
    "chunking": {
      "strategy": "fixed",
      "chunk_size": 200,
      "overlap": 100
    },
    "embedding": {
      "batch_size": 64
    },
    "retrieval": {
      "top_k": 10
    }
  },
  "machine": "UCA-NR-NBK-HL9"
}