{
  "model_name": "multilingual-e5",
  "language": "ru",
  "collection_name": "ru_common_multilingual_e5_chunk1000_overlap150",
  "total_questions": 169,
  "evaluated_questions": 169,
  "failed_questions": 0,
  "recall@1": 0.8165680473372781,
  "recall@3": 0.9881656804733728,
  "recall@5": 1.0,
  "mrr": 0.8974358974358976,
  "ndcg": 1.0528937259484148,
  "avg_latency_ms": 151.58556745568092,
  "median_latency_ms": 150.18029999919236,
  "run_id": "ru_common_multilingual-e5_ru_opio_Акции_и_новости_all_questions_ru.repaired.jsonl",
  "question_file": "opio_Акции_и_новости_all_questions_ru.repaired.jsonl",
  "question_file_path": "C:\\Users\\1000001392\\.vscode\\ru_common\\ru_ru_metadata\\opio\\opio_Акции_и_новости\\opio_Акции_и_новости_all_questions_ru.repaired.jsonl",
  "frozen": {
    "preprocessing": {
      "lowercase": false,
      "remove_special_chars": false,
      "strip_whitespace": true,
      "normalize_unicode": true
    },
    "chunking": {
      "strategy": "fixed",
      "chunk_size": 1000,
      "overlap": 150
    },
    "embedding": {
      "batch_size": 64
    },
    "retrieval": {
      "top_k": 10
    }
  },
  "machine": "UCA-NR-NBK-HL9"
}